girder_pytest_pyppeteer/__init__.py
girder_pytest_pyppeteer/main.py
girder_pytest_pyppeteer/plugin.py
girder_pytest_pyppeteer-0.0.12.dist-info/entry_points.txt
girder_pytest_pyppeteer-0.0.12.dist-info/LICENSE
girder_pytest_pyppeteer-0.0.12.dist-info/WHEEL
girder_pytest_pyppeteer-0.0.12.dist-info/METADATA
girder_pytest_pyppeteer-0.0.12.dist-info/RECORD
